aiportcountries/__init__.py
aiportcountries/aiportcountries.py
airportcountries-1.0.0.dist-info/METADATA
airportcountries-1.0.0.dist-info/WHEEL
airportcountries-1.0.0.dist-info/top_level.txt
airportcountries-1.0.0.dist-info/RECORD
