Metadata-Version: 2.1
Name: airportcountries
Version: 1.0.0
Summary: A library for storing airport country codes
Author: Chaitenya Kumar
Author-email: x21174211@student.ncirl.ie
Classifier: Development Status :: 4 - Beta
Classifier: Intended Audience :: Developers
Classifier: License :: OSI Approved :: MIT License
Classifier: Programming Language :: Python :: 3
Classifier: Programming Language :: Python :: 3.6
Classifier: Programming Language :: Python :: 3.7
Classifier: Programming Language :: Python :: 3.8
Classifier: Programming Language :: Python :: 3.9
